mer_lib/__init__.py
mer_lib/artefact_detection.py
mer_lib/data.py
mer_lib/feature_extraction.py
mer_lib/processor.py
mer_lib-0.1.dist-info/METADATA
mer_lib-0.1.dist-info/WHEEL
mer_lib-0.1.dist-info/top_level.txt
mer_lib-0.1.dist-info/RECORD
