Metadata-Version: 2.4
Name: MER_lib
Version: 0.1
Home-page: 
Author: Igor Varga
Author-email: ivarhauzh@gmail.com
Requires-Dist: numpy>=1.20.3
Requires-Dist: pyEDFlib>=0.1.22
Requires-Dist: scipy>=1.6.3
Requires-Dist: statsmodels
Dynamic: author
Dynamic: author-email
Dynamic: requires-dist
